landsatlook_stac-0.1.3.dist-info/licenses/LICENSE
landstac/__init__.py
landstac/auth.py
landstac/download.py
landstac/exceptions.py
landstac/read.py
landstac/stac.py
landstac/types.py
landstac/utils.py
landsatlook_stac-0.1.3.dist-info/METADATA
landsatlook_stac-0.1.3.dist-info/WHEEL
landsatlook_stac-0.1.3.dist-info/top_level.txt
landsatlook_stac-0.1.3.dist-info/RECORD
