Metadata-Version: 2.4
Name: landsatlook-stac
Version: 0.1.3
Summary: LandsatLook STAC search and authenticated asset access via ERS
Author-email: Pratyush Tripathy <pratkrt@gmail.com>
License: MIT License
Project-URL: Homepage, https://github.com/PratyushTripathy/landstac
Project-URL: Documentation, https://landstac.readthedocs.io/en/latest/
Project-URL: Issues, https://github.com/PratyushTripathy/landstac/issues
Keywords: STAC,Landsat,USGS,remote sensing,geospatial,COG
Classifier: Development Status :: 3 - Alpha
Classifier: Intended Audience :: Science/Research
Classifier: License :: OSI Approved :: MIT License
Classifier: Programming Language :: Python
Classifier: Programming Language :: Python :: 3
Classifier: Programming Language :: Python :: 3 :: Only
Classifier: Programming Language :: Python :: 3.9
Classifier: Programming Language :: Python :: 3.10
Classifier: Programming Language :: Python :: 3.11
Classifier: Topic :: Scientific/Engineering :: GIS
Classifier: Operating System :: OS Independent
Requires-Python: >=3.9
License-File: LICENSE
Requires-Dist: pystac-client>=0.7
Requires-Dist: requests>=2.31
Requires-Dist: rasterio>=1.3
Requires-Dist: rioxarray>=0.15
Requires-Dist: tqdm>=4.66
Requires-Dist: beautifulsoup4>=4.12
Dynamic: license-file
